main.py
Running_Calculator-1.7.0.dist-info/LICENSE.md
Running_Calculator-1.7.0.dist-info/METADATA
Running_Calculator-1.7.0.dist-info/WHEEL
Running_Calculator-1.7.0.dist-info/top_level.txt
Running_Calculator-1.7.0.dist-info/RECORD
