Metadata-Version: 2.1
Name: Running-Calculator
Version: 1.7.0
Summary: A running distance and speed command line interface. Measures in metric and imperial units, as well as marathons and half-marathons.
Home-page: https://github.com/willtheorangeguy/Running-Calculator
Author: willtheorangeguy
License: # GNU GENERAL PUBLIC LICENSE
Project-URL: Homepage, https://github.com/willtheorangeguy/Running-Calculator
Project-URL: Bug Tracker, https://github.com/willtheorangeguy/Running-Calculator/issues
Classifier: Development Status :: 5 - Production/Stable
Classifier: License :: OSI Approved :: GNU General Public License v3 (GPLv3)
Classifier: Natural Language :: English
Classifier: Operating System :: OS Independent
Classifier: Topic :: Scientific/Engineering :: Mathematics
Requires-Python: >=3.9
License-File: LICENSE.md
